camel_and_snake/__init__.py
camel_and_snake/converter.py
camel_and_snake-0.1.2.dist-info/METADATA
camel_and_snake-0.1.2.dist-info/RECORD
camel_and_snake-0.1.2.dist-info/WHEEL
camel_and_snake-0.1.2.dist-info/top_level.txt
