Metadata-Version: 2.1
Name: camel-and-snake
Version: 0.1.2
Summary: camelCase to snake_case or snake_case to camelCase for Python dict object
Home-page: https://github.com/Cphayim/camel-and-snake
Author: Cphayim
Author-email: admin@cphayim.me
Maintainer: 
Maintainer-email: 
License: MIT License
Platform: all
Classifier: Development Status :: 4 - Beta
Classifier: Operating System :: OS Independent
Classifier: Intended Audience :: Developers
Classifier: License :: OSI Approved :: MIT License
Classifier: Programming Language :: Python
Classifier: Programming Language :: Python :: Implementation
Classifier: Programming Language :: Python :: 3
Classifier: Programming Language :: Python :: 3.4
Classifier: Programming Language :: Python :: 3.5
Classifier: Programming Language :: Python :: 3.6
Classifier: Topic :: Software Development :: Libraries
